taranis_base_bot/__init__.py
taranis_base_bot/blueprint.py
taranis_base_bot/config.py
taranis_base_bot/decorators.py
taranis_base_bot/log.py
taranis_base_bot/misc.py
taranis_base_bot/protocols.py
taranis_base_bot-0.1.3.dist-info/licenses/LICENSE.md
taranis_base_bot-0.1.3.dist-info/METADATA
taranis_base_bot-0.1.3.dist-info/WHEEL
taranis_base_bot-0.1.3.dist-info/top_level.txt
taranis_base_bot-0.1.3.dist-info/RECORD
